usr/local/share/applications/youtube-downloader.desktop
usr/local/share/icons/hicolor/scalable/apps/youtube-downloader.svg
youtubedownloader/__init__.py
youtubedownloader/__main__.py
youtubedownloader/browser.py
youtubedownloader/component_changer.py
youtubedownloader/dialog_manager.py
youtubedownloader/download.py
youtubedownloader/logger.py
youtubedownloader/models.py
youtubedownloader/paths.py
youtubedownloader/settings.py
youtubedownloader/theme.py
youtubedownloader/version.py
youtubedownloader/database/__init__.py
youtubedownloader/database/models.py
youtubedownloader/qml/main.qml
youtubedownloader/qml/components/ApplicationHeader.qml
youtubedownloader/qml/components/ButtonWithBottomText.qml
youtubedownloader/qml/components/DialogHeader.qml
youtubedownloader/qml/components/Downloads.qml
youtubedownloader/qml/components/DropUrlInfo.qml
youtubedownloader/qml/components/Header.qml
youtubedownloader/qml/components/IconText.qml
youtubedownloader/qml/components/InputWithRemovableButton.qml
youtubedownloader/qml/components/OutputUrl.qml
youtubedownloader/qml/components/Separator.qml
youtubedownloader/qml/components/TileText.qml
youtubedownloader/qml/components/browser/BrowserTab.qml
youtubedownloader/qml/components/browser/BrowserTabs.qml
youtubedownloader/qml/components/browser/Browsers.qml
youtubedownloader/qml/components/download/DownloadButtons.qml
youtubedownloader/qml/components/download/DownloadItem.qml
youtubedownloader/qml/components/download/DownloadItemInfo.qml
youtubedownloader/qml/components/download/DownloadItems.qml
youtubedownloader/qml/components/download/DownloadOptions.qml
youtubedownloader/qml/components/download/DownloadStatus.qml
youtubedownloader/qml/components/download/DownloadStatusDetails.qml
youtubedownloader/qml/components/dynamic/Changer.qml
youtubedownloader/qml/components/format/FormatFile.qml
youtubedownloader/qml/components/format/FormatFileDescription.qml
youtubedownloader/qml/components/format/FormatFileDescriptionModel.qml
youtube_downloader-0.6.2.dist-info/LICENSE
youtube_downloader-0.6.2.dist-info/METADATA
youtube_downloader-0.6.2.dist-info/WHEEL
youtube_downloader-0.6.2.dist-info/entry_points.txt
youtube_downloader-0.6.2.dist-info/top_level.txt
youtube_downloader-0.6.2.dist-info/RECORD
