Metadata-Version: 2.1
Name: youtube-downloader
Version: 0.6.2
Summary: youtube-dl GUI simplify
Home-page: https://www.github.com/blooser/youtube-downloader
Author: blooser
Author-email: blooser@protonmail.com
License: GPLv3
Keywords: qt qml pyside2 youtube download youtube-dl
Platform: UNKNOWN
Classifier: Programming Language :: Python :: 3
Classifier: License :: OSI Approved :: GNU General Public License v3 (GPLv3)
Classifier: Development Status :: 2 - Pre-Alpha
Classifier: Environment :: X11 Applications :: Qt
Requires-Python: >=3.6
Requires-Dist: PySide2 (<=5.15.1)
Requires-Dist: lz4
Requires-Dist: sqlalchemy
Requires-Dist: beautifulsoup4
Requires-Dist: youtube-dl
